cap_sc_client/__init__.py
cap_sc_client/cap.py
cap_sc_client/client/__init__.py
cap_sc_client/client/base_client.py
cap_sc_client/client/base_model.py
cap_sc_client/client/client.py
cap_sc_client/client/cluster_types.py
cap_sc_client/client/create_session.py
cap_sc_client/client/dataset_initial_state_query.py
cap_sc_client/client/dataset_ready.py
cap_sc_client/client/download_urls.py
cap_sc_client/client/embedding_clusters.py
cap_sc_client/client/embedding_data.py
cap_sc_client/client/enums.py
cap_sc_client/client/exceptions.py
cap_sc_client/client/files_status.py
cap_sc_client/client/fragments.py
cap_sc_client/client/general_de.py
cap_sc_client/client/heatmap.py
cap_sc_client/client/highly_variable_genes.py
cap_sc_client/client/input_types.py
cap_sc_client/client/lookup_cells.py
cap_sc_client/client/md_commons_query.py
cap_sc_client/client/md_ready.py
cap_sc_client/client/search_datasets.py
cap_sc_client-1.0.1.dist-info/licenses/LICENSE
cap_sc_client-1.0.1.dist-info/METADATA
cap_sc_client-1.0.1.dist-info/WHEEL
cap_sc_client-1.0.1.dist-info/top_level.txt
cap_sc_client-1.0.1.dist-info/RECORD
